theme_gallery_utils/__init__.py
theme_gallery_utils/capturing.py
theme_gallery_utils/comparing.py
theme_gallery_utils/compressing.py
theme_gallery_utils/es_install.py
theme_gallery_utils/git_utils.py
theme_gallery_utils/markdown.py
theme_gallery_utils/parsing.py
theme_gallery_utils/paths.py
theme_gallery_utils/theme_gallery_utils.py
theme_gallery_utils/xml_utils.py
theme_gallery_utils/config/logging_dict.json
theme_gallery_utils/resources/es_systems.cfg
theme_gallery_utils/resources/downloaded_images/atari2600/Sample.Game-1-image.png
theme_gallery_utils/resources/downloaded_images/atari2600/Sample.Game-2-image.png
theme_gallery_utils/resources/downloaded_images/atari2600/Sample.Game-3-image.png
theme_gallery_utils/resources/gamelists/atari2600/gamelist.xml
theme_gallery_utils/resources/roms/atari2600/Sample.Game-1.bin
theme_gallery_utils/resources/roms/atari2600/Sample.Game-2.bin
theme_gallery_utils/resources/roms/atari2600/Sample.Game-3.bin
theme_gallery_utils/resources/roms/retropiemenu/sample.sh
theme_gallery_utils-0.3.1.dist-info/DESCRIPTION.rst
theme_gallery_utils-0.3.1.dist-info/METADATA
theme_gallery_utils-0.3.1.dist-info/RECORD
theme_gallery_utils-0.3.1.dist-info/WHEEL
theme_gallery_utils-0.3.1.dist-info/entry_points.txt
theme_gallery_utils-0.3.1.dist-info/metadata.json
theme_gallery_utils-0.3.1.dist-info/top_level.txt
