Metadata-Version: 2.0
Name: theme-gallery-utils
Version: 0.3.1
Summary: Collection of helpful utilities for maintaining the theme gallery repository.
Home-page: UNKNOWN
Author: Benjamin Dowell
Author-email: ben.dowell@gmail.com
License: MIT license
Keywords: theme_gallery_utils
Platform: UNKNOWN
Classifier: Development Status :: 4 - Beta
Classifier: Intended Audience :: Developers
Classifier: License :: OSI Approved :: MIT License
Classifier: Natural Language :: English
Classifier: Programming Language :: Python :: 3
Classifier: Programming Language :: Python :: 3.5
Classifier: Programming Language :: Python :: 3.6
Requires-Dist: lxml
